coval/__init__.py
coval/cli.py
coval/config/coval.config.yaml
coval/config/llm.config.yaml
coval/core/__init__.py
coval/core/cost_calculator.py
coval/core/iteration_manager.py
coval/deployers/__init__.py
coval/deployers/container_manager.py
coval/deployers/docker_deployer.py
coval/deployers/health_checker.py
coval/docker/__init__.py
coval/docker/deployment_manager.py
coval/engines/__init__.py
coval/engines/generation_engine.py
coval/engines/repair_engine.py
coval/generators/__init__.py
coval/generators/docker_generator.py
coval/generators/prompt_generator.py
coval/models/__init__.py
coval/models/generation_models.py
coval/parsers/__init__.py
coval/parsers/response_parser.py
coval/validators/__init__.py
coval/validators/content_cleaner.py
coval-2.0.30.dist-info/licenses/LICENSE
tests/__init__.py
tests/test_cli.py
tests/test_deployers.py
tests/test_generation_engine.py
coval-2.0.30.dist-info/METADATA
coval-2.0.30.dist-info/WHEEL
coval-2.0.30.dist-info/entry_points.txt
coval-2.0.30.dist-info/top_level.txt
coval-2.0.30.dist-info/RECORD
